[
    {
        "volt": 2.9772727272727275,
        "time": 0.0,
        "s": "1"
    },
    {
        "volt": 2.975,
        "time": 10.0,
        "s": "1"
    },
    {
        "volt": 2.975,
        "time": 20.0,
        "s": "1"
    },
    {
        "volt": 2.975,
        "time": 30.0,
        "s": "1"
    },
    {
        "volt": 2.975,
        "time": 40.0,
        "s": "1"
    },
    {
        "volt": 2.975,
        "time": 50.0,
        "s": "1"
    },
    {
        "volt": 2.975,
        "time": 60.0,
        "s": "1"
    },
    {
        "volt": 2.975,
        "time": 70.0,
        "s": "1"
    },
    {
        "volt": 2.975,
        "time": 80.0,
        "s": "1"
    },
    {
        "volt": 2.975,
        "time": 90.0,
        "s": "1"
    },
    {
        "volt": 2.975,
        "time": 100.0,
        "s": "1"
    },
    {
        "volt": 2.975,
        "time": 110.0,
        "s": "1"
    },
    {
        "volt": 2.975,
        "time": 120.0,
        "s": "1"
    },
    {
        "volt": 2.975,
        "time": 130.0,
        "s": "1"
    },
    {
        "volt": 2.9788413098236775,
        "time": 140.0,
        "s": "1"
    },
    {
        "volt": 2.9826826196473553,
        "time": 150.0,
        "s": "1"
    },
    {
        "volt": 2.986523929471033,
        "time": 160.0,
        "s": "1"
    },
    {
        "volt": 2.9903652392947104,
        "time": 170.0,
        "s": "1"
    },
    {
        "volt": 2.994206549118388,
        "time": 180.0,
        "s": "1"
    },
    {
        "volt": 2.998047858942065,
        "time": 190.0,
        "s": "1"
    },
    {
        "volt": 3.001889168765743,
        "time": 200.0,
        "s": "1"
    },
    {
        "volt": 3.0057304785894208,
        "time": 210.0,
        "s": "1"
    },
    {
        "volt": 3.009571788413098,
        "time": 220.0,
        "s": "1"
    },
    {
        "volt": 3.013413098236776,
        "time": 230.0,
        "s": "1"
    },
    {
        "volt": 3.0172544080604538,
        "time": 240.0,
        "s": "1"
    },
    {
        "volt": 3.021095717884131,
        "time": 250.0,
        "s": "1"
    },
    {
        "volt": 3.0249370277078085,
        "time": 260.0,
        "s": "1"
    },
    {
        "volt": 3.028778337531486,
        "time": 270.0,
        "s": "1"
    },
    {
        "volt": 3.0326196473551637,
        "time": 280.0,
        "s": "1"
    },
    {
        "volt": 3.036460957178841,
        "time": 290.0,
        "s": "1"
    },
    {
        "volt": 3.040302267002519,
        "time": 300.0,
        "s": "1"
    },
    {
        "volt": 3.0441435768261966,
        "time": 310.0,
        "s": "1"
    },
    {
        "volt": 3.047984886649874,
        "time": 320.0,
        "s": "1"
    },
    {
        "volt": 3.051826196473552,
        "time": 330.0,
        "s": "1"
    },
    {
        "volt": 3.0556675062972296,
        "time": 340.0,
        "s": "1"
    },
    {
        "volt": 3.0595088161209065,
        "time": 350.0,
        "s": "1"
    },
    {
        "volt": 3.0633501259445843,
        "time": 360.0,
        "s": "1"
    },
    {
        "volt": 3.0671914357682617,
        "time": 370.0,
        "s": "1"
    },
    {
        "volt": 3.0710327455919395,
        "time": 380.0,
        "s": "1"
    },
    {
        "volt": 3.0748740554156173,
        "time": 390.0,
        "s": "1"
    },
    {
        "volt": 3.0787153652392947,
        "time": 400.0,
        "s": "1"
    },
    {
        "volt": 3.0825566750629725,
        "time": 410.0,
        "s": "1"
    },
    {
        "volt": 3.0863979848866503,
        "time": 420.0,
        "s": "1"
    },
    {
        "volt": 3.0902392947103277,
        "time": 430.0,
        "s": "1"
    },
    {
        "volt": 3.094080604534005,
        "time": 440.0,
        "s": "1"
    },
    {
        "volt": 3.0979219143576824,
        "time": 450.0,
        "s": "1"
    },
    {
        "volt": 3.10176322418136,
        "time": 460.0,
        "s": "1"
    },
    {
        "volt": 3.1056045340050376,
        "time": 470.0,
        "s": "1"
    },
    {
        "volt": 3.1094458438287154,
        "time": 480.0,
        "s": "1"
    },
    {
        "volt": 3.113287153652393,
        "time": 490.0,
        "s": "1"
    },
    {
        "volt": 3.1171284634760705,
        "time": 500.0,
        "s": "1"
    },
    {
        "volt": 3.1209697732997483,
        "time": 510.0,
        "s": "1"
    },
    {
        "volt": 3.124811083123426,
        "time": 520.0,
        "s": "1"
    },
    {
        "volt": 3.1275,
        "time": 530.0,
        "s": "1"
    },
    {
        "volt": 3.12825,
        "time": 540.0,
        "s": "1"
    },
    {
        "volt": 3.13,
        "time": 550.0,
        "s": "1"
    },
    {
        "volt": 3.1310000000000002,
        "time": 560.0,
        "s": "1"
    },
    {
        "volt": 3.1405000000000003,
        "time": 570.0,
        "s": "1"
    },
    {
        "volt": 3.1645,
        "time": 580.0,
        "s": "1"
    },
    {
        "volt": 3.1735,
        "time": 590.0,
        "s": "1"
    },
    {
        "volt": 3.178611111111111,
        "time": 600.0,
        "s": "1"
    },
    {
        "volt": 3.1832499999999997,
        "time": 610.0,
        "s": "1"
    },
    {
        "volt": 3.18575,
        "time": 620.0,
        "s": "1"
    },
    {
        "volt": 3.1889999999999996,
        "time": 630.0,
        "s": "1"
    },
    {
        "volt": 3.19325,
        "time": 640.0,
        "s": "1"
    },
    {
        "volt": 3.19575,
        "time": 650.0,
        "s": "1"
    },
    {
        "volt": 3.19825,
        "time": 660.0,
        "s": "1"
    },
    {
        "volt": 3.2007499999999998,
        "time": 670.0,
        "s": "1"
    },
    {
        "volt": 3.2032499999999997,
        "time": 680.0,
        "s": "1"
    },
    {
        "volt": 3.20575,
        "time": 690.0,
        "s": "1"
    },
    {
        "volt": 3.20825,
        "time": 700.0,
        "s": "1"
    },
    {
        "volt": 3.2114999999999996,
        "time": 710.0,
        "s": "1"
    },
    {
        "volt": 3.21575,
        "time": 720.0,
        "s": "1"
    },
    {
        "volt": 3.2175,
        "time": 730.0,
        "s": "1"
    },
    {
        "volt": 3.21825,
        "time": 740.0,
        "s": "1"
    },
    {
        "volt": 3.22075,
        "time": 750.0,
        "s": "1"
    },
    {
        "volt": 3.2232499999999997,
        "time": 760.0,
        "s": "1"
    },
    {
        "volt": 3.2257499999999997,
        "time": 770.0,
        "s": "1"
    },
    {
        "volt": 3.2222500000000003,
        "time": 780.0,
        "s": "1"
    },
    {
        "volt": 3.21,
        "time": 790.0,
        "s": "1"
    },
    {
        "volt": 3.21,
        "time": 800.0,
        "s": "1"
    },
    {
        "volt": 3.21075,
        "time": 810.0,
        "s": "1"
    },
    {
        "volt": 3.2125,
        "time": 820.0,
        "s": "1"
    },
    {
        "volt": 3.2125,
        "time": 830.0,
        "s": "1"
    },
    {
        "volt": 3.21325,
        "time": 840.0,
        "s": "1"
    },
    {
        "volt": 3.2165,
        "time": 850.0,
        "s": "1"
    },
    {
        "volt": 3.22,
        "time": 860.0,
        "s": "1"
    },
    {
        "volt": 3.22,
        "time": 870.0,
        "s": "1"
    },
    {
        "volt": 3.22075,
        "time": 880.0,
        "s": "1"
    },
    {
        "volt": 3.2232499999999997,
        "time": 890.0,
        "s": "1"
    },
    {
        "volt": 3.225,
        "time": 900.0,
        "s": "1"
    },
    {
        "volt": 3.2257499999999997,
        "time": 910.0,
        "s": "1"
    },
    {
        "volt": 3.22825,
        "time": 920.0,
        "s": "1"
    },
    {
        "volt": 3.23,
        "time": 930.0,
        "s": "1"
    },
    {
        "volt": 3.2344999999999997,
        "time": 940.0,
        "s": "1"
    },
    {
        "volt": 3.245,
        "time": 950.0,
        "s": "1"
    },
    {
        "volt": 3.2457499999999997,
        "time": 960.0,
        "s": "1"
    },
    {
        "volt": 3.24825,
        "time": 970.0,
        "s": "1"
    },
    {
        "volt": 3.2514999999999996,
        "time": 980.0,
        "s": "1"
    },
    {
        "volt": 3.255,
        "time": 990.0,
        "s": "1"
    },
    {
        "volt": 3.2565,
        "time": 1000.0,
        "s": "1"
    },
    {
        "volt": 3.2615,
        "time": 1010.0,
        "s": "1"
    },
    {
        "volt": 3.265,
        "time": 1020.0,
        "s": "1"
    },
    {
        "volt": 3.2664999999999997,
        "time": 1030.0,
        "s": "1"
    },
    {
        "volt": 3.27,
        "time": 1040.0,
        "s": "1"
    },
    {
        "volt": 3.27075,
        "time": 1050.0,
        "s": "1"
    },
    {
        "volt": 3.27325,
        "time": 1060.0,
        "s": "1"
    },
    {
        "volt": 3.2765,
        "time": 1070.0,
        "s": "1"
    },
    {
        "volt": 3.28075,
        "time": 1080.0,
        "s": "1"
    },
    {
        "volt": 3.28325,
        "time": 1090.0,
        "s": "1"
    },
    {
        "volt": 3.285,
        "time": 1100.0,
        "s": "1"
    },
    {
        "volt": 3.2864999999999998,
        "time": 1110.0,
        "s": "1"
    },
    {
        "volt": 3.29,
        "time": 1120.0,
        "s": "1"
    },
    {
        "volt": 3.2914999999999996,
        "time": 1130.0,
        "s": "1"
    },
    {
        "volt": 3.29575,
        "time": 1140.0,
        "s": "1"
    },
    {
        "volt": 3.29825,
        "time": 1150.0,
        "s": "1"
    },
    {
        "volt": 3.30075,
        "time": 1160.0,
        "s": "1"
    },
    {
        "volt": 3.30325,
        "time": 1170.0,
        "s": "1"
    },
    {
        "volt": 3.305,
        "time": 1180.0,
        "s": "1"
    },
    {
        "volt": 3.3064999999999998,
        "time": 1190.0,
        "s": "1"
    },
    {
        "volt": 3.31075,
        "time": 1200.0,
        "s": "1"
    },
    {
        "volt": 3.31325,
        "time": 1210.0,
        "s": "1"
    },
    {
        "volt": 3.31575,
        "time": 1220.0,
        "s": "1"
    },
    {
        "volt": 3.31825,
        "time": 1230.0,
        "s": "1"
    },
    {
        "volt": 3.32075,
        "time": 1240.0,
        "s": "1"
    },
    {
        "volt": 3.32325,
        "time": 1250.0,
        "s": "1"
    },
    {
        "volt": 3.3257499999999998,
        "time": 1260.0,
        "s": "1"
    },
    {
        "volt": 3.3282499999999997,
        "time": 1270.0,
        "s": "1"
    }
]